{"rows": [{"queueTimeStamp": "2014/05/07-18:01:17", "minRate": "1MB", "queueNumber": "0", "txBytes": "10023961", "portNumber": "3", "queueRate": "0"}, {"queueTimeStamp": "2014/05/07-18:01:17", "minRate": "1MB", "queueNumber": "1", "txBytes": "0", "portNumber": "3", "queueRate": "0"}, {"queueTimeStamp": "2014/05/07-18:01:17", "minRate": "1MB", "queueNumber": "2", "txBytes": "0", "portNumber": "3", "queueRate": "0"}, {"queueTimeStamp": "2014/05/07-18:01:17", "minRate": "1MB", "queueNumber": "3", "txBytes": "0", "portNumber": "3", "queueRate": "0"}, {"queueTimeStamp": "2014/05/07-18:01:17", "minRate": "2MB", "queueNumber": "0", "txBytes": "45825", "portNumber": "2", "queueRate": "0"}, {"queueTimeStamp": "2014/05/07-18:01:17", "minRate": "2MB", "queueNumber": "1", "txBytes": "0", "portNumber": "2", "queueRate": "0"}, {"queueTimeStamp": "2014/05/07-18:01:17", "minRate": "1MB", "queueNumber": "2", "txBytes": "0", "portNumber": "2", "queueRate": "0"}, {"queueTimeStamp": "2014/05/07-18:01:17", "minRate": "0MB", "queueNumber": "3", "txBytes": "0", "portNumber": "2", "queueRate": "0"}, {"queueTimeStamp": "2014/05/07-18:01:17", "minRate": "1MB", "queueNumber": "0", "txBytes": "10024004", "portNumber": "5", "queueRate": "0"}, {"queueTimeStamp": "2014/05/07-18:01:17", "minRate": "1MB", "queueNumber": "1", "txBytes": "0", "portNumber": "5", "queueRate": "0"}, {"queueTimeStamp": "2014/05/07-18:01:17", "minRate": "1MB", "queueNumber": "2", "txBytes": "0", "portNumber": "5", "queueRate": "0"}, {"queueTimeStamp": "2014/05/07-18:01:17", "minRate": "1MB", "queueNumber": "3", "txBytes": "0", "portNumber": "5", "queueRate": "0"}, {"queueTimeStamp": "2014/05/07-18:01:17", "minRate": "1MB", "queueNumber": "0", "txBytes": "10023961", "portNumber": "4", "queueRate": "0"}, {"queueTimeStamp": "2014/05/07-18:01:17", "minRate": "1MB", "queueNumber": "1", "txBytes": "0", "portNumber": "4", "queueRate": "0"}, {"queueTimeStamp": "2014/05/07-18:01:17", "minRate": "1MB", "queueNumber": "2", "txBytes": "0", "portNumber": "4", "queueRate": "0"}, {"queueTimeStamp": "2014/05/07-18:01:17", "minRate": "1MB", "queueNumber": "3", "txBytes": "0", "portNumber": "4", "queueRate": "0"}, {"queueTimeStamp": "2014/05/07-18:01:17", "minRate": "1MB", "queueNumber": "0", "txBytes": "10023898", "portNumber": "1", "queueRate": "0"}, {"queueTimeStamp": "2014/05/07-18:01:17", "minRate": "1MB", "queueNumber": "1", "txBytes": "0", "portNumber": "1", "queueRate": "0"}, {"queueTimeStamp": "2014/05/07-18:01:17", "minRate": "1MB", "queueNumber": "2", "txBytes": "0", "portNumber": "1", "queueRate": "0"}, {"queueTimeStamp": "2014/05/07-18:01:17", "minRate": "1MB", "queueNumber": "3", "txBytes": "0", "portNumber": "1", "queueRate": "0"}], "tableType": "4", "tableSize": "20"}